packfun/__init__.py
packfun/fn_fun.py
packfun/tas_fun.py
packfun-1.dist-info/LICENSE
packfun-1.dist-info/WHEEL
packfun-1.dist-info/METADATA
packfun-1.dist-info/RECORD
