Metadata-Version: 2.1
Name: packfun
Version: 1
Summary: nothing
Author: Lapkin
Classifier: License :: OSI Approved :: MIT License
